{"(0.1, 0.3, 0.4, 0.2, 0.0)": "neutral", "(0.0, 0.2, 0.8, 0.1, 0.0)": "happiness", "(0.1, 0.5, 0.2, 0.1, 0.1)": "surprise", "(0.1, 0.3, 0.3, 0.2, 0.1)": "happiness", "(0.1, 0.4, 0.2, 0.3, 0.1)": "neutral", "(0.2, 0.5, 0.3, 0.0, 0.0)": "disgust", "(0.0, 0.1, 0.5, 0.4, 0.0)": "fear", "(0.0, 0.1, 0.8, 0.1, 0.0)": "happiness", "(0.0, 0.0, 0.1, 0.5, 0.4)": "disgust", "(0.2, 0.4, 0.1, 0.2, 0.1)": "anger", "(0.1, 0.5, 0.1, 0.2, 0.1)": "anger", "(0.1, 0.7, 0.2, 0.1, 0.0)": "happiness", "(0.4, 0.4, 0.1, 0.0, 0.0)": "sadness", "(0.2, 0.5, 0.1, 0.2, 0.0)": "disgust", "(0.1, 0.2, 0.1, 0.4, 0.1)": "anger", "(0.0, 0.1, 0.4, 0.5, 0.1)": "surprise", "(0.4, 0.4, 0.2, 0.0, 0.0)": "fear", "(0.0, 0.2, 0.3, 0.4, 0.1)": "surprise", "(0.4, 0.6, 0.1, 0.0, 0.0)": "disgust", "(0.0, 0.1, 0.1, 0.5, 0.3)": "surprise", "(0.2, 0.5, 0.1, 0.1, 0.0)": "anger", "(0.1, 0.1, 0.2, 0.5, 0.2)": "anger", "(0.1, 0.2, 0.3, 0.3, 0.1)": "fear", "(0.0, 0.4, 0.4, 0.1, 0.0)": "disgust", "(0.1, 0.3, 0.2, 0.3, 0.1)": "neutral", "(0.1, 0.6, 0.1, 0.1, 0.0)": "neutral", "(0.0, 0.0, 0.0, 0.7, 0.2)": "surprise", "(0.0, 0.0, 0.0, 0.6, 0.4)": "fear", "(0.1, 0.5, 0.4, 0.1, 0.0)": "happiness", "(0.0, 0.0, 0.5, 0.4, 0.0)": "anger", "(0.1, 0.4, 0.4, 0.0, 0.0)": "fear", "(0.3, 0.5, 0.1, 0.1, 0.1)": "disgust", "(0.3, 0.5, 0.2, 0.0, 0.0)": "neutral", "(0.0, 0.5, 0.5, 0.0, 0.0)": "neutral", "(0.1, 0.7, 0.2, 0.0, 0.0)": "fear", "(0.0, 0.0, 0.3, 0.6, 0.1)": "neutral", "(0.1, 0.5, 0.5, 0.0, 0.0)": "happiness", "(0.3, 0.6, 0.1, 0.0, 0.0)": "neutral", "(0.2, 0.3, 0.1, 0.2, 0.2)": "disgust", "(0.1, 0.4, 0.4, 0.2, 0.0)": "neutral", "(0.1, 0.5, 0.2, 0.2, 0.0)": "surprise", "(0.3, 0.4, 0.1, 0.1, 0.2)": "fear", "(0.0, 0.2, 0.6, 0.2, 0.0)": "anger", "(0.0, 0.2, 0.3, 0.4, 0.0)": "happiness", "(0.0, 0.0, 0.8, 0.1, 0.0)": "happiness", "(0.0, 0.1, 0.1, 0.6, 0.3)": "surprise", "(0.0, 0.1, 0.1, 0.5, 0.2)": "neutral", "(0.0, 0.2, 0.4, 0.3, 0.1)": "disgust", "(0.1, 0.4, 0.2, 0.3, 0.0)": "neutral", "(0.1, 0.4, 0.3, 0.2, 0.0)": "neutral", "(0.1, 0.3, 0.3, 0.3, 0.0)": "anger", "(0.0, 0.0, 0.1, 0.6, 0.3)": "happiness", "(0.0, 0.1, 0.5, 0.4, 0.1)": "neutral", "(0.0, 0.5, 0.4, 0.0, 0.0)": "surprise", "(0.0, 0.4, 0.4, 0.2, 0.0)": "anger", "(0.0, 0.0, 0.1, 0.7, 0.1)": "neutral", "(0.0, 0.1, 0.6, 0.2, 0.0)": "surprise", "(0.0, 0.0, 0.2, 0.6, 0.2)": "fear", "(0.0, 0.0, 0.0, 0.5, 0.5)": "neutral", "(0.0, 0.2, 0.5, 0.2, 0.0)": "neutral", "(0.0, 0.1, 0.5, 0.3, 0.0)": "neutral", "(0.3, 0.6, 0.0, 0.0, 0.0)": "surprise", "(0.0, 0.0, 0.9, 0.1, 0.0)": "neutral", "(0.0, 0.1, 0.4, 0.4, 0.1)": "happiness", "(0.1, 0.3, 0.2, 0.4, 0.1)": "happiness", "(0.1, 0.6, 0.3, 0.1, 0.0)": "anger", "(0.1, 0.1, 0.1, 0.5, 0.2)": "neutral", "(0.0, 0.2, 0.2, 0.4, 0.1)": "disgust", "(0.0, 0.0, 0.2, 0.7, 0.1)": "anger", "(0.0, 0.2, 0.2, 0.6, 0.1)": "surprise", "(0.0, 0.3, 0.4, 0.1, 0.0)": "neutral", "(0.3, 0.4, 0.1, 0.1, 0.1)": "anger", "(0.1, 0.7, 0.1, 0.1, 0.0)": "neutral", "(0.0, 0.1, 0.3, 0.6, 0.0)": "neutral", "(0.0, 0.1, 0.1, 0.5, 0.1)": "happiness", "(0.0, 0.0, 0.0, 0.4, 0.6)": "surprise", "(0.0, 0.2, 0.4, 0.3, 0.0)": "happiness", "(0.0, 0.2, 0.5, 0.3, 0.0)": "happiness", "(0.1, 0.4, 0.3, 0.2, 0.1)": "happiness", "(0.1, 0.3, 0.3, 0.3, 0.1)": "happiness", "(0.0, 0.2, 0.4, 0.2, 0.0)": "happiness", "(0.0, 0.0, 0.9, 0.0, 0.0)": "fear", "(0.0, 0.3, 0.4, 0.3, 0.0)": "disgust", "(0.2, 0.5, 0.2, 0.1, 0.0)": "happiness", "(0.0, 0.0, 0.0, 0.5, 0.4)": "happiness", "(0.0, 0.0, 1.0, 0.0, 0.0)": "neutral", "(0.1, 0.8, 0.1, 0.0, 0.0)": "anger", "(0.2, 0.6, 0.2, 0.1, 0.0)": "anger", "(0.0, 0.1, 0.4, 0.4, 0.0)": "fear", "(0.0, 0.1, 0.1, 0.6, 0.2)": "surprise", "(0.0, 0.2, 0.6, 0.1, 0.0)": "neutral", "(0.3, 0.4, 0.0, 0.2, 0.1)": "happiness", "(0.0, 0.1, 0.3, 0.5, 0.1)": "neutral", "(0.1, 0.5, 0.1, 0.1, 0.1)": "disgust", "(0.1, 0.5, 0.4, 0.0, 0.0)": "anger", "(0.0, 0.1, 0.0, 0.6, 0.2)": "fear", "(0.0, 0.0, 0.0, 0.8, 0.2)": "happiness", "(0.1, 0.2, 0.2, 0.4, 0.1)": "neutral", "(0.1, 0.5, 0.3, 0.2, 0.0)": "anger", "(0.0, 0.2, 0.2, 0.4, 0.0)": "neutral", "(0.0, 0.1, 0.3, 0.6, 0.1)": "anger", "(0.0, 0.1, 0.1, 0.7, 0.1)": "fear", "(0.0, 0.2, 0.2, 0.5, 0.1)": "fear", "(0.0, 0.0, 0.4, 0.5, 0.1)": "neutral", "(0.2, 0.7, 0.1, 0.1, 0.0)": "neutral", "(0.1, 0.5, 0.2, 0.2, 0.1)": "disgust", "(0.0, 0.4, 0.6, 0.0, 0.0)": "disgust", "(0.1, 0.4, 0.2, 0.2, 0.1)": "anger", "(0.1, 0.2, 0.1, 0.5, 0.2)": "disgust", "(0.1, 0.6, 0.2, 0.1, 0.0)": "neutral", "(0.2, 0.5, 0.0, 0.2, 0.1)": "anger", "(0.0, 0.0, 0.1, 0.6, 0.2)": "surprise", "(0.0, 0.3, 0.6, 0.0, 0.0)": "neutral", "(0.1, 0.1, 0.2, 0.5, 0.1)": "neutral", "(0.2, 0.5, 0.2, 0.1, 0.1)": "happiness", "(0.1, 0.5, 0.3, 0.1, 0.0)": "neutral", "(0.1, 0.3, 0.1, 0.3, 0.2)": "happiness", "(0.1, 0.7, 0.1, 0.0, 0.0)": "fear", "(0.0, 0.3, 0.4, 0.2, 0.0)": "surprise", "(0.2, 0.3, 0.1, 0.3, 0.2)": "disgust", "(0.1, 0.1, 0.1, 0.4, 0.3)": "fear", "(0.1, 0.3, 0.1, 0.3, 0.1)": "surprise", "(0.0, 0.1, 0.3, 0.5, 0.0)": "fear", "(0.0, 0.0, 0.1, 0.7, 0.2)": "anger", "(0.2, 0.6, 0.1, 0.1, 0.1)": "neutral", "(0.0, 0.6, 0.3, 0.0, 0.0)": "happiness", "(0.0, 0.0, 0.1, 0.8, 0.2)": "neutral", "(0.2, 0.7, 0.2, 0.0, 0.0)": "happiness", "(0.1, 0.2, 0.0, 0.4, 0.3)": "fear", "(0.1, 0.7, 0.3, 0.0, 0.0)": "neutral", "(0.3, 0.5, 0.0, 0.1, 0.1)": "fear", "(0.0, 0.2, 0.3, 0.5, 0.1)": "neutral", "(0.5, 0.5, 0.0, 0.0, 0.0)": "disgust", "(0.0, 0.3, 0.6, 0.1, 0.0)": "disgust", "(0.3, 0.6, 0.2, 0.0, 0.0)": "neutral", "(0.5, 0.4, 0.1, 0.0, 0.0)": "sadness", "(0.0, 0.2, 0.7, 0.1, 0.0)": "happiness", "(0.1, 0.4, 0.2, 0.2, 0.0)": "disgust", "(0.0, 0.1, 0.2, 0.7, 0.0)": "happiness", "(0.0, 0.0, 0.7, 0.2, 0.0)": "happiness", "(0.0, 0.0, 0.4, 0.6, 0.0)": "neutral", "(0.5, 0.4, 0.0, 0.0, 0.0)": "sadness", "(0.0, 0.3, 0.7, 0.0, 0.0)": "disgust", "(0.0, 0.0, 0.7, 0.3, 0.0)": "anger", "(0.0, 0.0, 0.1, 0.8, 0.1)": "happiness", "(0.0, 0.1, 0.2, 0.5, 0.1)": "anger", "(0.8, 0.2, 0.0, 0.0, 0.0)": "neutral", "(0.0, 0.3, 0.3, 0.3, 0.0)": "happiness", "(0.0, 0.1, 0.2, 0.6, 0.1)": "happiness", "(0.0, 0.0, 0.0, 0.4, 0.5)": "surprise", "(0.4, 0.5, 0.0, 0.0, 0.0)": "surprise", "(0.0, 0.1, 0.9, 0.0, 0.0)": "disgust", "(0.0, 0.1, 0.8, 0.0, 0.0)": "anger", "(0.1, 0.6, 0.1, 0.0, 0.0)": "surprise", "(0.0, 0.0, 0.8, 0.2, 0.0)": "surprise", "(0.0, 0.2, 0.4, 0.4, 0.0)": "surprise", "(0.0, 0.1, 0.2, 0.5, 0.2)": "neutral", "(0.1, 0.2, 0.1, 0.5, 0.1)": "surprise", "(0.1, 0.2, 0.2, 0.4, 0.2)": "neutral", "(0.3, 0.7, 0.0, 0.0, 0.0)": "fear", "(0.1, 0.4, 0.3, 0.1, 0.0)": "fear", "(0.1, 0.4, 0.1, 0.3, 0.1)": "disgust", "(0.1, 0.6, 0.2, 0.0, 0.0)": "neutral", "(0.1, 0.3, 0.5, 0.0, 0.0)": "surprise", "(0.4, 0.5, 0.1, 0.0, 0.0)": "anger", "(0.1, 0.4, 0.6, 0.0, 0.0)": "neutral", "(0.1, 0.5, 0.2, 0.1, 0.0)": "anger", "(0.1, 0.1, 0.3, 0.4, 0.1)": "anger", "(0.0, 0.1, 0.1, 0.6, 0.1)": "disgust", "(0.1, 0.4, 0.1, 0.2, 0.1)": "happiness", "(0.0, 0.1, 0.2, 0.7, 0.1)": "neutral", "(0.1, 0.4, 0.5, 0.1, 0.0)": "anger", "(0.0, 0.0, 0.1, 0.3, 0.6)": "anger", "(0.0, 0.1, 0.7, 0.3, 0.0)": "happiness", "(0.1, 0.4, 0.5, 0.0, 0.0)": "anger", "(0.1, 0.3, 0.4, 0.2, 0.1)": "surprise", "(0.6, 0.3, 0.1, 0.0, 0.0)": "fear", "(0.1, 0.5, 0.2, 0.0, 0.0)": "surprise", "(0.2, 0.6, 0.1, 0.1, 0.0)": "disgust", "(0.2, 0.6, 0.3, 0.0, 0.0)": "surprise", "(0.0, 0.4, 0.3, 0.2, 0.0)": "neutral", "(0.0, 0.1, 0.2, 0.6, 0.0)": "neutral", "(0.1, 0.1, 0.2, 0.4, 0.2)": "neutral", "(0.1, 0.6, 0.3, 0.0, 0.0)": "anger", "(0.1, 0.5, 0.3, 0.0, 0.0)": "anger", "(0.0, 0.1, 0.3, 0.4, 0.1)": "surprise", "(0.2, 0.6, 0.2, 0.0, 0.0)": "anger", "(0.0, 0.1, 0.0, 0.4, 0.4)": "fear", "(0.0, 0.6, 0.4, 0.0, 0.0)": "fear", "(0.0, 0.4, 0.5, 0.0, 0.0)": "disgust", "(0.3, 0.5, 0.1, 0.0, 0.0)": "anger", "(0.2, 0.6, 0.1, 0.0, 0.0)": "anger", "(0.0, 0.0, 0.0, 0.8, 0.1)": "neutral", "(0.0, 0.0, 0.2, 0.8, 0.1)": "fear", "(0.0, 0.1, 0.7, 0.2, 0.0)": "happiness", "(0.0, 0.0, 0.6, 0.4, 0.0)": "happiness", "(0.0, 0.0, 0.4, 0.5, 0.0)": "disgust", "(0.0, 0.3, 0.3, 0.4, 0.1)": "surprise", "(0.2, 0.7, 0.1, 0.0, 0.0)": "neutral", "(0.0, 0.3, 0.5, 0.1, 0.0)": "neutral", "(0.0, 0.1, 0.5, 0.3, 0.1)": "neutral", "(0.0, 0.2, 0.7, 0.0, 0.0)": "anger", "(0.0, 0.1, 0.4, 0.3, 0.1)": "anger", "(0.1, 0.4, 0.4, 0.1, 0.0)": "neutral", "(0.0, 0.0, 0.1, 0.5, 0.3)": "happiness", "(0.0, 0.2, 0.8, 0.0, 0.0)": "surprise", "(0.0, 0.1, 0.9, 0.1, 0.0)": "happiness", "(0.0, 0.0, 0.0, 0.6, 0.3)": "happiness", "(0.0, 0.4, 0.5, 0.1, 0.0)": "neutral", "(0.0, 0.1, 0.4, 0.5, 0.0)": "neutral", "(0.2, 0.5, 0.2, 0.0, 0.0)": "disgust", "(0.0, 0.1, 0.7, 0.1, 0.0)": "disgust", "(0.2, 0.5, 0.1, 0.1, 0.1)": "neutral", "(0.0, 0.4, 0.3, 0.3, 0.0)": "fear", "(0.0, 0.5, 0.4, 0.1, 0.0)": "neutral", "(0.0, 0.0, 0.0, 0.7, 0.3)": "fear", "(0.0, 0.3, 0.5, 0.2, 0.0)": "happiness"}